README.rst
setup.py
winjob/__init__.py
winjob/winjob.py
winjob.egg-info/PKG-INFO
winjob.egg-info/SOURCES.txt
winjob.egg-info/dependency_links.txt
winjob.egg-info/requires.txt
winjob.egg-info/top_level.txt