Metadata-Version: 1.1
Name: winjob
Version: 0.0.12
Summary: Parser for Windows Scheduled Task files
Home-page: http://github.com/yahoo/winjob
Author: Sean Gillespie
Author-email: seagill@yahoo-inc.com
License: LICENSE.txt
Platform: UNKNOWN
Classifier: License :: OSI Approved :: BSD License
Classifier: Operating System :: POSIX :: Linux
Classifier: Programming Language :: Python
